exhaust/__init__.py
exhaust-1.1.0.dist-info/LICENSE
exhaust-1.1.0.dist-info/WHEEL
exhaust-1.1.0.dist-info/METADATA
exhaust-1.1.0.dist-info/RECORD
