Metadata-Version: 2.1
Name: exhaust
Version: 1.1.0
Summary: Exhaustively enumerate a combinatorial space represented by a function
Author-email: Maik Riechert <maik.riechert@arcor.de>
Requires-Python: >=3.7
Classifier: License :: OSI Approved :: MIT License
Project-URL: Changelog, https://github.com/letmaik/exhaust/blob/main/CHANGELOG.md
Project-URL: Documentation, https://github.com/letmaik/exhaust
Project-URL: Source, https://github.com/letmaik/exhaust
